AutoTS/AutoTS.py
AutoTS/__init__.py
AutoTS/utils/CandidateModel.py
AutoTS/utils/__init__.py
AutoTS/utils/error_metrics.py
AutoTS/utils/validation.py
auto_bots/AutoTS.py
auto_bots/__init__.py
auto_bots/utils/CandidateModel.py
auto_bots/utils/__init__.py
auto_bots/utils/error_metrics.py
auto_bots/utils/validation.py
auto_bots-0.0.4.dist-info/LICENSE
auto_bots-0.0.4.dist-info/METADATA
auto_bots-0.0.4.dist-info/WHEEL
auto_bots-0.0.4.dist-info/top_level.txt
auto_bots-0.0.4.dist-info/RECORD
