Metadata-Version: 2.1
Name: auto-bots
Version: 0.0.4
Summary: Automated time-series forecasting
Home-page: https://github.com/awalker88/auto-bots
Author: Andrew Walker
Author-email: awalker88@me.com
License: UNKNOWN
Platform: UNKNOWN
Classifier: Programming Language :: Python :: 3 :: Only
Classifier: License :: OSI Approved :: MIT License
Classifier: Development Status :: 4 - Beta
Requires-Dist: pandas (>=1.2.0)
Requires-Dist: pmdarima (>=1.8.0)
Requires-Dist: tbats (>=1.1.0)
Requires-Dist: statsmodels (>=0.12.2)
